myfunx/__init__.py
myfunx/client.py
myfunx/json_manager.py
myfunx-0.5.7.dist-info/LICENSE
myfunx-0.5.7.dist-info/METADATA
myfunx-0.5.7.dist-info/WHEEL
myfunx-0.5.7.dist-info/top_level.txt
myfunx-0.5.7.dist-info/RECORD
