Metadata-Version: 2.1
Name: myfunx
Version: 0.5.7
Author: unixtux
License: GNU GENERAL PUBLIC LICENSE
Requires-Python: >=3.8
License-File: LICENSE
Requires-Dist: aiotgm
